{
  "generator-jhipster": {
    "applicationType": "monolith",
    "authenticationType": "jwt",
    "baseName": "jhipsterGmaoApplication",
    "blueprints": [],
    "buildTool": "gradle",
    "cacheProvider": "ehcache",
    "clientFramework": "react",
    "clientPackageManager": "npm",
    "creationTimestamp": 1725976578894,
    "databaseType": "sql",
    "devDatabaseType": "h2Disk",
    "devServerPort": 9060,
    "enableHibernateCache": true,
    "enableSwaggerCodegen": "true",
    "enableTranslation": true,
    "entities": [],
    "gitCompany": "",
    "jhiPrefix": "jhi",
    "jhipsterVersion": "8.7.0",
    "jwtSecretKey": "MDU1MDc2ZmEwNGJmNDQxZTZjMTA4OTM3MDY4Nzk4MDllYTgwZjM3YzE1MDM4ZWU4ZTlhY2MxYmFhZDA2MzFiNjc4ODY2MzYyYjVlZjY5YzYwMDEzMDk0Mjg5MmE1ZWIzNWQzOGU4M2UzZjEyYTQ0YThhYWJkN2NjMjMxOGFkMGM=",
    "languages": ["en", "ar-ly", "fr"],
    "messageBroker": "kafka",
    "nativeLanguage": "en",
    "packageFolder": "com/bnbdigitech/gmao",
    "packageName": "com.bnbdigitech.gmao",
    "prodDatabaseType": "mysql",
    "searchEngine": "elasticsearch",
    "serverPort": 80081,
    "serviceDiscoveryType": false,
    "testFrameworks": [],
    "useSass": true,
    "websocket": "spring-websocket",
    "withAdminUi": true
  },
  "git-company": "HBouzouf20",
  "git-provider": "GitHub",
  "repository-name": "gmao-application"
}
